currency_conversion/__init__.py
currency_conversion/audusd.py
currency_conversion/eurusd.py
currency_conversion/gbpeur.py
currency_conversion/usdcad.py
currency_conversion/usdcny.py
currency_conversion/usdczk.py
currency_conversion/usdinr.py
currency_conversion/usdjpy.py
currency_conversion/usdmxn.py
currency_conversion/usdpln.py
currency_conversion-1.1.1.dist-info/METADATA
currency_conversion-1.1.1.dist-info/WHEEL
currency_conversion-1.1.1.dist-info/top_level.txt
currency_conversion-1.1.1.dist-info/RECORD
